yahoo_finance_cache/__init__.py
yahoo_finance_cache/yahoo_data_reader_cached.py
yahoo_finance_cache-0.1.3.dist-info/WHEEL
yahoo_finance_cache-0.1.3.dist-info/METADATA
yahoo_finance_cache-0.1.3.dist-info/RECORD
