Metadata-Version: 2.1
Name: yahoo-finance-cache
Version: 0.1.3
Summary: 
Author: IsaacBreen
Author-email: 57783927+IsaacBreen@users.noreply.github.com
Requires-Python: >=3.8,<4.0
Classifier: Programming Language :: Python :: 3
Classifier: Programming Language :: Python :: 3.10
Classifier: Programming Language :: Python :: 3.8
Classifier: Programming Language :: Python :: 3.9
Requires-Dist: dateparser (>=1.1.1,<2.0.0)
Requires-Dist: pandas (>=1.4.3,<2.0.0)
Requires-Dist: pandas-datareader (>=0.10.0,<0.11.0)
